{
    "version": "1.3.0",
    "architecture": {
        "32bit": {
            "url": "https://github.com/ldez/gti/releases/download/v1.3.0/gti_v1.3.0_windows_386.zip",
            "bin": [
                "gti.exe"
            ],
            "hash": "36eb03410cd0496bebece4b2eae8feb8953bb361b57b42842e81adb5cabb5802"
        },
        "64bit": {
            "url": "https://github.com/ldez/gti/releases/download/v1.3.0/gti_v1.3.0_windows_amd64.zip",
            "bin": [
                "gti.exe"
            ],
            "hash": "3db7cf8008b69309e506573a1757b4d5da23eaa0108ee2d905b9aa19a3d6724a"
        }
    },
    "homepage": "https://github.com/ldez/gti",
    "license": "APACHE",
    "description": "Just a silly git launcher, basically. Inspired by sl."
}